gua/__init__.py
gua/gua.py
gua-1.0.3.2.dist-info/METADATA
gua-1.0.3.2.dist-info/WHEEL
gua-1.0.3.2.dist-info/entry_points.txt
gua-1.0.3.2.dist-info/top_level.txt
gua-1.0.3.2.dist-info/zip-safe
gua-1.0.3.2.dist-info/RECORD
