Metadata-Version: 2.1
Name: gua
Version: 1.0.3.2
Summary: gua. 卦. 心诚则灵.
Home-page: http://github.com/lhnonline/gua
Author: lhnonline
Author-email: 0376lhn@gmail.com
License: GPLv3
Keywords: gua,卦
Platform: UNKNOWN
Classifier: Programming Language :: Python
Classifier: Programming Language :: Python :: 3
Classifier: License :: OSI Approved :: GNU General Public License v3 (GPLv3)
Classifier: Operating System :: OS Independent
